pointdistance/PointDistance.py
pointdistance/__init__.py
pointdistance-0.0.1.dist-info/LICENSE
pointdistance-0.0.1.dist-info/METADATA
pointdistance-0.0.1.dist-info/WHEEL
pointdistance-0.0.1.dist-info/top_level.txt
pointdistance-0.0.1.dist-info/RECORD
