Metadata-Version: 2.1
Name: pointdistance
Version: 0.0.1
Summary: Find distance between points
Home-page: UNKNOWN
Author: Abdullah Reza
Author-email: UNKNOWN
License: UNKNOWN
Platform: UNKNOWN
